scrapyrta/__init__.py
scrapyrta/cli.py
scrapyrta/app/__init__.py
scrapyrta/app/app.py
scrapyrta/app/services.py
scrapyrta/app/api/__init__.py
scrapyrta/app/api/v1/__init__.py
scrapyrta/app/api/v1/crawls.py
scrapyrta/app/core/__init__.py
scrapyrta/app/core/exceptions.py
scrapyrta/app/core/log.py
scrapyrta/app/core/utils.py
scrapyrta/app/core/config/__init__.py
scrapyrta/app/core/config/default_settings.py
scrapyrta/app/core/config/spider_settings.py
scrapyrta/app/schemas/__init__.py
scrapyrta/app/schemas/crawl.py
scrapyrta/app/utils/__init__.py
scrapyrta/app/utils/metaclasses.py
scrapyrta/logs/.gitkeep
scrapyrta-1.0.5.dist-info/METADATA
scrapyrta-1.0.5.dist-info/WHEEL
scrapyrta-1.0.5.dist-info/entry_points.txt
scrapyrta-1.0.5.dist-info/licenses/LICENSE.txt
scrapyrta-1.0.5.dist-info/RECORD
