Metadata-Version: 2.4
Name: scrapyrta
Version: 1.0.5
Summary: Asynchronous HTTP API for Running Scrapy Spiders
Project-URL: Repository, https://github.com/farhaduneci/scrapyrta
Project-URL: Releases, https://github.com/farhaduneci/scrapyrta/releases
Author-email: Farhad Uneci <farhaduneci@gmail.com>
License: MIT License
License-File: LICENSE.txt
Keywords: fastapi,scrapy,scrapyrt
Classifier: Development Status :: 4 - Beta
Classifier: Framework :: FastAPI
Classifier: License :: OSI Approved :: MIT License
Classifier: Operating System :: OS Independent
Classifier: Programming Language :: Python :: 3.9
Classifier: Programming Language :: Python :: 3.10
Classifier: Programming Language :: Python :: 3.11
Classifier: Programming Language :: Python :: 3.12
Classifier: Programming Language :: Python :: 3.13
Requires-Python: >=3.9
Requires-Dist: crochet>=2.1.1
Requires-Dist: fastapi>=0.115.12
Requires-Dist: loguru>=0.7.3
Requires-Dist: pydantic>=2.11.3
Requires-Dist: python-environ>=0.4.54
Requires-Dist: requests>=2.32.3
Requires-Dist: scrapy>=2.8.0
Requires-Dist: uvicorn[standard]>=0.34.2
